{
  "key": [
    "stance-detection-part-1",
    "emonet-m1",
    "mj_data_54_U1.png"
  ],
  "value": {
    "Physical and Exhaustive States|Fatigue/Exhaustion": 2.5605359258464513,
    "Positive Low-Energy Emotions|Contemplation": 2.5490218624131473,
    "Negative Low-Energy Emotions|Sadness": 1.6606120024882376,
    "Negative High-Energy Emotions|Distress": 1.3387318119174723,
    "Positive Low-Energy Emotions|Affection": 1.2905424955393097,
    "Positive High-Energy Emotions|Interest": 1.1351196011289573,
    "Cognitive States and Processes|Concentration": 1.031793144882926,
    "Positive Low-Energy Emotions|Contentment": 1.031622748310258,
    "Positive High-Energy Emotions|Pleasure/Ecstasy": 0.9713906484861873,
    "Positive Low-Energy Emotions|Pride": 0.9205998880345196,
    "Positive High-Energy Emotions|Hope/Enthusiasm/Optimism": 0.7604285224439787,
    "Extra Dimensions|Dominance": 0.6115010225695077,
    "Physical and Exhaustive States|Pain": 0.6102023081640503,
    "Negative Low-Energy Emotions|Helplessness": 0.5892655669264631,
    "Negative Low-Energy Emotions|Emotional Numbness": 0.57133818679786,
    "Negative High-Energy Emotions|Anger": 0.5283097406446715,
    "Positive High-Energy Emotions|Amusement": 0.368556007456321,
    "Negative High-Energy Emotions|Impatience and Irritability": 0.2914471053091925,
    "Positive Low-Energy Emotions|Relief": 0.0012757624994158313,
    "Negative Low-Energy Emotions|Jealousy & Envy": 0.0,
    "Positive High-Energy Emotions|Awe": -0.002824253037626491,
    "Physical and Exhaustive States|Sourness": -0.017605013019599755,
    "Physical and Exhaustive States|Intoxication/Altered States of Consciousness": -0.0232992918049787,
    "Negative High-Energy Emotions|Disgust": -0.027253193910414482,
    "Positive High-Energy Emotions|Astonishment/Surprise": -0.04018755607825496,
    "Positive High-Energy Emotions|Triumph": -0.0751229721401228,
    "Extra Dimensions|Emotional Vulnerability": -0.10900112888315228,
    "Negative High-Energy Emotions|Fear": -0.11000048151860634,
    "Positive High-Energy Emotions|Teasing": -0.11136329796970328,
    "Negative Low-Energy Emotions|Embarrassment": -0.11897844662923952,
    "Positive High-Energy Emotions|Elation": -0.15317161323299144,
    "Cognitive States and Processes|Confusion": -0.1788294174241059,
    "Negative Low-Energy Emotions|Contempt": -0.3743256655429582,
    "Positive Low-Energy Emotions|Thankfulness/Gratitude": -0.4801284670740223,
    "Longing & Lust|Longing": -0.5164033403217574,
    "Negative High-Energy Emotions|Malevolence/Malice": -0.5297952059028677,
    "Extra Dimensions|Arousal": -0.5423408831868852,
    "Negative Low-Energy Emotions|Shame": -0.6558857626079551,
    "Longing & Lust|Sexual Lust": -0.6798239438197552,
    "Negative Low-Energy Emotions|Disappointment": -0.7285905931820418,
    "Negative Low-Energy Emotions|Doubt": -0.936570955999025,
    "Extra Dimensions|Valence": -1.3586509381804697,
    "Longing & Lust|Infatuation": -1.6303870764598523,
    "Negative Low-Energy Emotions|Bitterness": -1.8312757350982
  }
}