{
  "key": [
    "projects",
    "empathic-insight-face-large",
    "juggernaut-xl-v8-prompt-6-83_result.png"
  ],
  "value": {
    "Negative High-Energy Emotions|Malevolence/Malice": -0.2411337483959164,
    "Negative Low-Energy Emotions|Jealousy & Envy": 0.7024210252919618,
    "Longing & Lust|Infatuation": -2.0927711315058612,
    "Cognitive States and Processes|Confusion": 0.5410258705590796,
    "Longing & Lust|Sexual Lust": -1.1461051131083684,
    "Positive High-Energy Emotions|Hope/Enthusiasm/Optimism": -1.3543785554126782,
    "Positive High-Energy Emotions|Interest": -1.851501095481217,
    "Positive High-Energy Emotions|Elation": -2.440855667312794,
    "Negative Low-Energy Emotions|Disappointment": 3.645702521820717,
    "Negative High-Energy Emotions|Distress": 2.0951092067010264,
    "Positive Low-Energy Emotions|Contemplation": 0.1714110334524337,
    "Negative Low-Energy Emotions|Emotional Numbness": 0.023145881604184123,
    "Negative High-Energy Emotions|Impatience and Irritability": 1.123701329343021,
    "Negative Low-Energy Emotions|Helplessness": 1.7434814971334793,
    "Negative Low-Energy Emotions|Contempt": 0.9824696660436252,
    "Positive High-Energy Emotions|Astonishment/Surprise": -0.6956604629382492,
    "Positive High-Energy Emotions|Pleasure/Ecstasy": -1.2727397806241232,
    "Negative Low-Energy Emotions|Doubt": 0.28887508411124785,
    "Negative High-Energy Emotions|Anger": 1.647234255671501,
    "Positive Low-Energy Emotions|Contentment": -1.4135082611507355,
    "Positive Low-Energy Emotions|Relief": -1.5043046035398455,
    "Positive High-Energy Emotions|Amusement": -2.5734706034971513,
    "Longing & Lust|Longing": 0.6612998449450413,
    "Positive High-Energy Emotions|Awe": -0.6006864232832894,
    "Physical and Exhaustive States|Fatigue/Exhaustion": 1.042123948478085,
    "Negative Low-Energy Emotions|Bitterness": 0.8466144323874922,
    "Negative High-Energy Emotions|Disgust": 1.6021304500891882,
    "Positive Low-Energy Emotions|Thankfulness/Gratitude": -2.045007233509027,
    "Positive High-Energy Emotions|Teasing": -1.6350932984163657,
    "Physical and Exhaustive States|Intoxication/Altered States of Consciousness": -0.27647888579351054,
    "Positive Low-Energy Emotions|Pride": -1.9624315929303275,
    "Negative Low-Energy Emotions|Embarrassment": -0.3434369734411731,
    "Positive Low-Energy Emotions|Affection": -0.2445306399026338,
    "Negative Low-Energy Emotions|Sadness": 1.8553851007363376,
    "Negative Low-Energy Emotions|Shame": 0.25164759099264356,
    "Positive High-Energy Emotions|Triumph": -1.9014499009882702,
    "Cognitive States and Processes|Concentration": 0.07734316622947945,
    "Physical and Exhaustive States|Sourness": 0.08124537223950029,
    "Physical and Exhaustive States|Pain": 1.2792438673096544,
    "Negative High-Energy Emotions|Fear": 0.6760727967913536
  }
}