{
  "key": [
    "projects",
    "empathic-insight-face-large",
    "juggernaut-xl-v8-prompt-5-72_result.png"
  ],
  "value": {
    "Negative High-Energy Emotions|Malevolence/Malice": -0.37218552718925135,
    "Negative Low-Energy Emotions|Jealousy & Envy": -0.022210522635894625,
    "Longing & Lust|Infatuation": -1.155630428304567,
    "Cognitive States and Processes|Confusion": -0.5010062520529199,
    "Longing & Lust|Sexual Lust": -0.907956662256928,
    "Positive High-Energy Emotions|Hope/Enthusiasm/Optimism": -0.2570609790042919,
    "Positive High-Energy Emotions|Interest": -0.3971009137108922,
    "Positive High-Energy Emotions|Elation": -1.6123186800081064,
    "Negative Low-Energy Emotions|Disappointment": 1.9944999921519089,
    "Negative High-Energy Emotions|Distress": 1.600044352079139,
    "Positive Low-Energy Emotions|Contemplation": 1.275885339559001,
    "Negative Low-Energy Emotions|Emotional Numbness": -0.5502895814070807,
    "Negative High-Energy Emotions|Impatience and Irritability": 0.18434208165854216,
    "Negative Low-Energy Emotions|Helplessness": -0.40635939422775713,
    "Negative Low-Energy Emotions|Contempt": 0.2642737508214572,
    "Positive High-Energy Emotions|Astonishment/Surprise": -0.1572776943072678,
    "Positive High-Energy Emotions|Pleasure/Ecstasy": -0.11243225403568324,
    "Negative Low-Energy Emotions|Doubt": 0.7960093428583487,
    "Negative High-Energy Emotions|Anger": 0.7672004050016401,
    "Positive Low-Energy Emotions|Contentment": -0.24824794620932922,
    "Positive Low-Energy Emotions|Relief": -0.8475467719663592,
    "Positive High-Energy Emotions|Amusement": -1.6420755496336257,
    "Longing & Lust|Longing": -0.08732996348086197,
    "Positive High-Energy Emotions|Awe": -0.21267401407308428,
    "Physical and Exhaustive States|Fatigue/Exhaustion": 0.020363648676258728,
    "Negative Low-Energy Emotions|Bitterness": 1.1869842827846022,
    "Negative High-Energy Emotions|Disgust": 0.2962563855244833,
    "Positive Low-Energy Emotions|Thankfulness/Gratitude": 0.8326411200676334,
    "Positive High-Energy Emotions|Teasing": -1.0672232775499717,
    "Physical and Exhaustive States|Intoxication/Altered States of Consciousness": -0.3037966481683885,
    "Positive Low-Energy Emotions|Pride": 0.09902014018200775,
    "Negative Low-Energy Emotions|Embarrassment": -0.02223862921052122,
    "Positive Low-Energy Emotions|Affection": 1.0598387501082,
    "Negative Low-Energy Emotions|Sadness": 0.022421634092050446,
    "Negative Low-Energy Emotions|Shame": -0.21785146057824878,
    "Positive High-Energy Emotions|Triumph": -0.8632320584093823,
    "Cognitive States and Processes|Concentration": 0.3543806675646235,
    "Physical and Exhaustive States|Sourness": -0.13329504972323775,
    "Physical and Exhaustive States|Pain": -0.3257357669753187,
    "Negative High-Energy Emotions|Fear": -0.06020847895785297
  }
}