{
  "key": [
    "projects",
    "empathic-insight-face-large",
    "mj_data_267_U4.png"
  ],
  "value": {
    "Negative High-Energy Emotions|Malevolence/Malice": -0.7855299104289974,
    "Negative Low-Energy Emotions|Jealousy & Envy": -0.6833445272287901,
    "Longing & Lust|Infatuation": -1.0669561214350602,
    "Cognitive States and Processes|Confusion": -0.1282687251593042,
    "Longing & Lust|Sexual Lust": -1.6901274348094182,
    "Positive High-Energy Emotions|Hope/Enthusiasm/Optimism": -0.24866244613686028,
    "Positive High-Energy Emotions|Interest": -0.2822631480172276,
    "Positive High-Energy Emotions|Elation": 2.116642608920879,
    "Negative Low-Energy Emotions|Disappointment": 2.1274476754862595,
    "Negative High-Energy Emotions|Distress": -0.0027788457625052554,
    "Positive Low-Energy Emotions|Contemplation": 1.4271004160055343,
    "Negative Low-Energy Emotions|Emotional Numbness": -1.6266366940627204,
    "Negative High-Energy Emotions|Impatience and Irritability": -0.5859964536502957,
    "Negative Low-Energy Emotions|Helplessness": -0.14013167205978838,
    "Negative Low-Energy Emotions|Contempt": -0.587822091539993,
    "Positive High-Energy Emotions|Astonishment/Surprise": -0.21241556700319064,
    "Positive High-Energy Emotions|Pleasure/Ecstasy": 2.3158621662066263,
    "Negative Low-Energy Emotions|Doubt": -0.32479438584133546,
    "Negative High-Energy Emotions|Anger": -0.13228470623493216,
    "Positive Low-Energy Emotions|Contentment": -0.8683055290645538,
    "Positive Low-Energy Emotions|Relief": 0.9282973549734144,
    "Positive High-Energy Emotions|Amusement": 2.956652511088725,
    "Longing & Lust|Longing": -0.11104331377688248,
    "Positive High-Energy Emotions|Awe": -0.10434328744954913,
    "Physical and Exhaustive States|Fatigue/Exhaustion": 0.4712192912334029,
    "Negative Low-Energy Emotions|Bitterness": 0.17594273095621782,
    "Negative High-Energy Emotions|Disgust": 1.1127050740315634,
    "Positive Low-Energy Emotions|Thankfulness/Gratitude": 1.0789174986992252,
    "Positive High-Energy Emotions|Teasing": -0.12050047204994108,
    "Physical and Exhaustive States|Intoxication/Altered States of Consciousness": -0.43140935816747294,
    "Positive Low-Energy Emotions|Pride": -0.26051225705839254,
    "Negative Low-Energy Emotions|Embarrassment": 1.7978097030038342,
    "Positive Low-Energy Emotions|Affection": 2.403382041200119,
    "Negative Low-Energy Emotions|Sadness": 1.2272436975380954,
    "Negative Low-Energy Emotions|Shame": -0.3512682324669817,
    "Positive High-Energy Emotions|Triumph": -1.749155265215565,
    "Cognitive States and Processes|Concentration": -0.9211464520719121,
    "Physical and Exhaustive States|Sourness": -0.13734315877780318,
    "Physical and Exhaustive States|Pain": -0.023135144798194673,
    "Negative High-Energy Emotions|Fear": -0.8314466867749306
  }
}