{
  "key": [
    "projects",
    "empathic-insight-face-large",
    "mj_data_48_U3.png"
  ],
  "value": {
    "Negative High-Energy Emotions|Malevolence/Malice": 0.4039521824283634,
    "Negative Low-Energy Emotions|Jealousy & Envy": -0.0476273736795958,
    "Longing & Lust|Infatuation": -0.7020906991862199,
    "Cognitive States and Processes|Confusion": -0.0960632627035547,
    "Longing & Lust|Sexual Lust": 2.0124712114737315,
    "Positive High-Energy Emotions|Hope/Enthusiasm/Optimism": 0.12418379962882575,
    "Positive High-Energy Emotions|Interest": 0.4594772351905704,
    "Positive High-Energy Emotions|Elation": 0.9741538312833975,
    "Negative Low-Energy Emotions|Disappointment": -0.30674238918239594,
    "Negative High-Energy Emotions|Distress": 1.2841267409570076,
    "Positive Low-Energy Emotions|Contemplation": -0.7802046577325639,
    "Negative Low-Energy Emotions|Emotional Numbness": -1.8388258916030036,
    "Negative High-Energy Emotions|Impatience and Irritability": 0.1761390520259738,
    "Negative Low-Energy Emotions|Helplessness": 1.2542123001463272,
    "Negative Low-Energy Emotions|Contempt": 0.32516490224967987,
    "Positive High-Energy Emotions|Astonishment/Surprise": 0.8096361250057815,
    "Positive High-Energy Emotions|Pleasure/Ecstasy": 2.0612621777460856,
    "Negative Low-Energy Emotions|Doubt": -1.128165919592823,
    "Negative High-Energy Emotions|Anger": 1.265509778857231,
    "Positive Low-Energy Emotions|Contentment": -2.3988288292354523,
    "Positive Low-Energy Emotions|Relief": -1.0407816924680682,
    "Positive High-Energy Emotions|Amusement": 1.8986003922210897,
    "Longing & Lust|Longing": 0.5756921970492284,
    "Positive High-Energy Emotions|Awe": 0.19128084947519453,
    "Physical and Exhaustive States|Fatigue/Exhaustion": -0.04572544500889142,
    "Negative Low-Energy Emotions|Bitterness": 0.2393018723060103,
    "Negative High-Energy Emotions|Disgust": 0.5481844765736776,
    "Positive Low-Energy Emotions|Thankfulness/Gratitude": -0.06515622604747895,
    "Positive High-Energy Emotions|Teasing": -0.31338354633354093,
    "Physical and Exhaustive States|Intoxication/Altered States of Consciousness": 1.0934435360791053,
    "Positive Low-Energy Emotions|Pride": -0.36625104962683774,
    "Negative Low-Energy Emotions|Embarrassment": -1.8981864622717395,
    "Positive Low-Energy Emotions|Affection": 0.1621277115187224,
    "Negative Low-Energy Emotions|Sadness": -0.5867169738867704,
    "Negative Low-Energy Emotions|Shame": -0.748415411116884,
    "Positive High-Energy Emotions|Triumph": -0.9371556462084546,
    "Cognitive States and Processes|Concentration": 0.2620933059427668,
    "Physical and Exhaustive States|Sourness": -0.24415033107623457,
    "Physical and Exhaustive States|Pain": 1.1308450507241137,
    "Negative High-Energy Emotions|Fear": 1.7106663342411903
  }
}