{
  "key": [
    "projects",
    "empathic-insight-face-large",
    "mj_data_325_U4.png"
  ],
  "value": {
    "Negative High-Energy Emotions|Malevolence/Malice": -0.9711802590923275,
    "Negative Low-Energy Emotions|Jealousy & Envy": -1.798084541305023,
    "Longing & Lust|Infatuation": -1.9643762893580339,
    "Cognitive States and Processes|Confusion": -2.1804778640295437,
    "Longing & Lust|Sexual Lust": -0.9643724585368352,
    "Positive High-Energy Emotions|Hope/Enthusiasm/Optimism": 2.246822978858562,
    "Positive High-Energy Emotions|Interest": 0.8642763612791896,
    "Positive High-Energy Emotions|Elation": 1.7037754800718496,
    "Negative Low-Energy Emotions|Disappointment": 0.5468537020880508,
    "Negative High-Energy Emotions|Distress": -0.7690178332083366,
    "Positive Low-Energy Emotions|Contemplation": 0.9876260717519942,
    "Negative Low-Energy Emotions|Emotional Numbness": -0.6183303695807563,
    "Negative High-Energy Emotions|Impatience and Irritability": 0.7553412271663547,
    "Negative Low-Energy Emotions|Helplessness": 0.08704177554915937,
    "Negative Low-Energy Emotions|Contempt": -1.3484479307733914,
    "Positive High-Energy Emotions|Astonishment/Surprise": 0.49921155873686063,
    "Positive High-Energy Emotions|Pleasure/Ecstasy": 2.903177606384544,
    "Negative Low-Energy Emotions|Doubt": -2.4477573226003306,
    "Negative High-Energy Emotions|Anger": 1.3785640543699262,
    "Positive Low-Energy Emotions|Contentment": 2.5617071738773407,
    "Positive Low-Energy Emotions|Relief": -0.4066578902830096,
    "Positive High-Energy Emotions|Amusement": 1.3022954353975023,
    "Longing & Lust|Longing": 1.0233347348144333,
    "Positive High-Energy Emotions|Awe": 1.2412265019600883,
    "Physical and Exhaustive States|Fatigue/Exhaustion": -0.0001572172409470829,
    "Negative Low-Energy Emotions|Bitterness": -1.4199680566261796,
    "Negative High-Energy Emotions|Disgust": -1.1657314675257486,
    "Positive Low-Energy Emotions|Thankfulness/Gratitude": 0.5156834078941714,
    "Positive High-Energy Emotions|Teasing": -0.9974258808901205,
    "Physical and Exhaustive States|Intoxication/Altered States of Consciousness": -0.5511134854791795,
    "Positive Low-Energy Emotions|Pride": 1.0356097984423531,
    "Negative Low-Energy Emotions|Embarrassment": -1.697902934897472,
    "Positive Low-Energy Emotions|Affection": 2.4132096550306854,
    "Negative Low-Energy Emotions|Sadness": -0.49575349103001987,
    "Negative Low-Energy Emotions|Shame": -1.1424128419182757,
    "Positive High-Energy Emotions|Triumph": -0.8523276866709485,
    "Cognitive States and Processes|Concentration": -0.3285484906461309,
    "Physical and Exhaustive States|Sourness": -1.5301332974992692,
    "Physical and Exhaustive States|Pain": 0.677835147293175,
    "Negative High-Energy Emotions|Fear": -0.01623956301852192
  }
}