{
  "key": [
    "projects",
    "empathic-insight-face-large",
    "mj_data_147_U1.png"
  ],
  "value": {
    "Negative High-Energy Emotions|Malevolence/Malice": 0.3794273744983707,
    "Negative Low-Energy Emotions|Jealousy & Envy": 0.10197146321920791,
    "Longing & Lust|Infatuation": -1.5782767124079606,
    "Cognitive States and Processes|Confusion": -1.9386947219396997,
    "Longing & Lust|Sexual Lust": -1.1331988001658635,
    "Positive High-Energy Emotions|Hope/Enthusiasm/Optimism": -0.2658847314075512,
    "Positive High-Energy Emotions|Interest": -0.4841880680993199,
    "Positive High-Energy Emotions|Elation": -1.4395496103364755,
    "Negative Low-Energy Emotions|Disappointment": 0.04311970951145172,
    "Negative High-Energy Emotions|Distress": 0.23046384480069665,
    "Positive Low-Energy Emotions|Contemplation": 0.377932000637931,
    "Negative Low-Energy Emotions|Emotional Numbness": -1.0342522364745246,
    "Negative High-Energy Emotions|Impatience and Irritability": 0.37228220235556364,
    "Negative Low-Energy Emotions|Helplessness": -0.295175393258824,
    "Negative Low-Energy Emotions|Contempt": 2.012428152600632,
    "Positive High-Energy Emotions|Astonishment/Surprise": -0.8128241210803391,
    "Positive High-Energy Emotions|Pleasure/Ecstasy": 0.34684036902645055,
    "Negative Low-Energy Emotions|Doubt": -0.5487885664014475,
    "Negative High-Energy Emotions|Anger": 0.9585482424497602,
    "Positive Low-Energy Emotions|Contentment": -2.0681403526729523,
    "Positive Low-Energy Emotions|Relief": -1.1368023910154315,
    "Positive High-Energy Emotions|Amusement": 0.19128702971207745,
    "Longing & Lust|Longing": 0.0004545652514378329,
    "Positive High-Energy Emotions|Awe": -0.6358393354231819,
    "Physical and Exhaustive States|Fatigue/Exhaustion": 0.11454453065334003,
    "Negative Low-Energy Emotions|Bitterness": 1.3146620214511366,
    "Negative High-Energy Emotions|Disgust": 1.1960150224759298,
    "Positive Low-Energy Emotions|Thankfulness/Gratitude": 1.458797450176276,
    "Positive High-Energy Emotions|Teasing": -0.5273146300127401,
    "Physical and Exhaustive States|Intoxication/Altered States of Consciousness": 0.15994525036829366,
    "Positive Low-Energy Emotions|Pride": 0.8263710308184519,
    "Negative Low-Energy Emotions|Embarrassment": -0.36837043081574583,
    "Positive Low-Energy Emotions|Affection": 0.3879166922411498,
    "Negative Low-Energy Emotions|Sadness": 0.18645123232813443,
    "Negative Low-Energy Emotions|Shame": -0.09520596325616626,
    "Positive High-Energy Emotions|Triumph": -0.6133310915266766,
    "Cognitive States and Processes|Concentration": 0.0023786429140497667,
    "Physical and Exhaustive States|Sourness": 0.3297106578759849,
    "Physical and Exhaustive States|Pain": 1.1317705320435412,
    "Negative High-Energy Emotions|Fear": -0.5758173857037636
  }
}