{
  "key": [
    "projects",
    "empathic-insight-face-large",
    "mj_data_134_U4.png"
  ],
  "value": {
    "Negative High-Energy Emotions|Malevolence/Malice": -1.0623705972270931,
    "Negative Low-Energy Emotions|Jealousy & Envy": -1.866617485030609,
    "Longing & Lust|Infatuation": -0.8286171741389177,
    "Cognitive States and Processes|Confusion": -2.9412424628759792,
    "Longing & Lust|Sexual Lust": -0.7215443278147893,
    "Positive High-Energy Emotions|Hope/Enthusiasm/Optimism": 3.5119983214183765,
    "Positive High-Energy Emotions|Interest": 1.4061063645407557,
    "Positive High-Energy Emotions|Elation": 6.4299608018797105,
    "Negative Low-Energy Emotions|Disappointment": -1.4805116247933578,
    "Negative High-Energy Emotions|Distress": -2.603966968988671,
    "Positive Low-Energy Emotions|Contemplation": -0.962010029970723,
    "Negative Low-Energy Emotions|Emotional Numbness": -2.3499693375716313,
    "Negative High-Energy Emotions|Impatience and Irritability": -0.9825225519016385,
    "Negative Low-Energy Emotions|Helplessness": -2.1583777267091415,
    "Negative Low-Energy Emotions|Contempt": -1.244123589953079,
    "Positive High-Energy Emotions|Astonishment/Surprise": -0.042669883333146696,
    "Positive High-Energy Emotions|Pleasure/Ecstasy": 3.529537545959739,
    "Negative Low-Energy Emotions|Doubt": -2.157272894194569,
    "Negative High-Energy Emotions|Anger": -0.02851731121540091,
    "Positive Low-Energy Emotions|Contentment": 5.786225234561545,
    "Positive Low-Energy Emotions|Relief": 2.4255110464464216,
    "Positive High-Energy Emotions|Amusement": 6.007364262072917,
    "Longing & Lust|Longing": 0.022877713406650235,
    "Positive High-Energy Emotions|Awe": 0.3281434850876823,
    "Physical and Exhaustive States|Fatigue/Exhaustion": -0.9534666340118821,
    "Negative Low-Energy Emotions|Bitterness": -1.4703578233192949,
    "Negative High-Energy Emotions|Disgust": -0.734821833889274,
    "Positive Low-Energy Emotions|Thankfulness/Gratitude": 5.371639962307013,
    "Positive High-Energy Emotions|Teasing": 0.6338540048787699,
    "Physical and Exhaustive States|Intoxication/Altered States of Consciousness": 0.3205139049054946,
    "Positive Low-Energy Emotions|Pride": 1.3725324440112008,
    "Negative Low-Energy Emotions|Embarrassment": -0.6607251337652698,
    "Positive Low-Energy Emotions|Affection": 3.711882092698532,
    "Negative Low-Energy Emotions|Sadness": -1.0052791477301541,
    "Negative Low-Energy Emotions|Shame": -1.4187883740685443,
    "Positive High-Energy Emotions|Triumph": 0.44277502882130004,
    "Cognitive States and Processes|Concentration": -1.4562841054227422,
    "Physical and Exhaustive States|Sourness": -0.7221215272508561,
    "Physical and Exhaustive States|Pain": -0.711814363090431,
    "Negative High-Energy Emotions|Fear": -1.4729864988629433
  }
}