{
  "key": [
    "projects",
    "empathic-insight-face-large",
    "mj_data_31_U2.png"
  ],
  "value": {
    "Negative High-Energy Emotions|Malevolence/Malice": -0.5047926295833554,
    "Negative Low-Energy Emotions|Jealousy & Envy": 0.3413867511907045,
    "Longing & Lust|Infatuation": -0.823120195379152,
    "Cognitive States and Processes|Confusion": 1.0347504551385474,
    "Longing & Lust|Sexual Lust": 0.7174594973728938,
    "Positive High-Energy Emotions|Hope/Enthusiasm/Optimism": -1.0754526597217602,
    "Positive High-Energy Emotions|Interest": 0.274367761425674,
    "Positive High-Energy Emotions|Elation": -1.438632652481251,
    "Negative Low-Energy Emotions|Disappointment": 3.630240719338112,
    "Negative High-Energy Emotions|Distress": 2.057019454503761,
    "Positive Low-Energy Emotions|Contemplation": 0.6448879202017013,
    "Negative Low-Energy Emotions|Emotional Numbness": -1.7719306450972663,
    "Negative High-Energy Emotions|Impatience and Irritability": -0.2921515153720975,
    "Negative Low-Energy Emotions|Helplessness": 1.2344350617773392,
    "Negative Low-Energy Emotions|Contempt": -0.8399568914972684,
    "Positive High-Energy Emotions|Astonishment/Surprise": 0.511454591192305,
    "Positive High-Energy Emotions|Pleasure/Ecstasy": 0.4873559945032877,
    "Negative Low-Energy Emotions|Doubt": -0.057824157437528764,
    "Negative High-Energy Emotions|Anger": 1.2911258286237715,
    "Positive Low-Energy Emotions|Contentment": -3.2556222328609405,
    "Positive Low-Energy Emotions|Relief": -1.4000823058713885,
    "Positive High-Energy Emotions|Amusement": -0.07523656991255634,
    "Longing & Lust|Longing": 0.5345388257151524,
    "Positive High-Energy Emotions|Awe": 0.047958262461949897,
    "Physical and Exhaustive States|Fatigue/Exhaustion": 0.1411486466163222,
    "Negative Low-Energy Emotions|Bitterness": -0.2378879069756059,
    "Negative High-Energy Emotions|Disgust": 0.5125687939717489,
    "Positive Low-Energy Emotions|Thankfulness/Gratitude": -0.9167623566474545,
    "Positive High-Energy Emotions|Teasing": -0.9314083723833456,
    "Physical and Exhaustive States|Intoxication/Altered States of Consciousness": -0.13547074713689433,
    "Positive Low-Energy Emotions|Pride": -1.437728686321746,
    "Negative Low-Energy Emotions|Embarrassment": -0.030504482138682842,
    "Positive Low-Energy Emotions|Affection": 0.9973219415983733,
    "Negative Low-Energy Emotions|Sadness": 0.30212268818827237,
    "Negative Low-Energy Emotions|Shame": -0.39603203594903735,
    "Positive High-Energy Emotions|Triumph": -1.9231912912165416,
    "Cognitive States and Processes|Concentration": 0.19009131228660836,
    "Physical and Exhaustive States|Sourness": -0.6081482673250138,
    "Physical and Exhaustive States|Pain": 1.261163751991356,
    "Negative High-Energy Emotions|Fear": 1.2247156407530693
  }
}