{
  "key": [
    "stance-detection-part-9",
    "emonet-m1",
    "flux_prompt_9-image_204.png"
  ],
  "value": {
    "Positive High-Energy Emotions|Pleasure/Ecstasy": 3.577279372813275,
    "Positive High-Energy Emotions|Amusement": 3.3129476752991858,
    "Positive Low-Energy Emotions|Contentment": 3.0583017873117226,
    "Positive High-Energy Emotions|Elation": 2.444595440220944,
    "Positive Low-Energy Emotions|Affection": 2.3274523141886014,
    "Extra Dimensions|Valence": 1.8869730080094107,
    "Positive High-Energy Emotions|Hope/Enthusiasm/Optimism": 1.398551557874887,
    "Cognitive States and Processes|Concentration": 1.356063631714591,
    "Positive Low-Energy Emotions|Pride": 1.2593137723881573,
    "Extra Dimensions|Emotional Vulnerability": 0.6671841452409932,
    "Extra Dimensions|Dominance": 0.6069915139597359,
    "Negative High-Energy Emotions|Anger": 0.444868721586444,
    "Negative High-Energy Emotions|Impatience and Irritability": 0.2991793774573248,
    "Positive Low-Energy Emotions|Thankfulness/Gratitude": 0.23348310683818102,
    "Physical and Exhaustive States|Fatigue/Exhaustion": 0.1537840547374426,
    "Positive Low-Energy Emotions|Relief": 0.009518555880629973,
    "Negative Low-Energy Emotions|Jealousy & Envy": 0.0,
    "Physical and Exhaustive States|Sourness": -0.008941515154399714,
    "Physical and Exhaustive States|Pain": -0.020670116004905786,
    "Positive High-Energy Emotions|Awe": -0.02209242303674911,
    "Physical and Exhaustive States|Intoxication/Altered States of Consciousness": -0.02365085490102515,
    "Negative High-Energy Emotions|Disgust": -0.038930909837776924,
    "Positive High-Energy Emotions|Astonishment/Surprise": -0.04713654868823268,
    "Positive Low-Energy Emotions|Contemplation": -0.06371829662158168,
    "Positive High-Energy Emotions|Triumph": -0.07525827747773066,
    "Extra Dimensions|Arousal": -0.07537783043725144,
    "Negative Low-Energy Emotions|Emotional Numbness": -0.08002828544640272,
    "Positive High-Energy Emotions|Interest": -0.11485417282734156,
    "Negative Low-Energy Emotions|Embarrassment": -0.122740639653398,
    "Negative High-Energy Emotions|Fear": -0.13001400015006462,
    "Positive High-Energy Emotions|Teasing": -0.1687263983196064,
    "Negative Low-Energy Emotions|Helplessness": -0.18424195362998672,
    "Cognitive States and Processes|Confusion": -0.1887595214413636,
    "Negative Low-Energy Emotions|Contempt": -0.3761867088173608,
    "Negative High-Energy Emotions|Malevolence/Malice": -0.541791214358621,
    "Negative High-Energy Emotions|Distress": -0.6446670428150412,
    "Negative Low-Energy Emotions|Shame": -0.65675981908878,
    "Longing & Lust|Sexual Lust": -0.6904689459464489,
    "Negative Low-Energy Emotions|Disappointment": -0.7426494438876654,
    "Longing & Lust|Longing": -0.8622703557431479,
    "Negative Low-Energy Emotions|Doubt": -0.9313746845347963,
    "Negative Low-Energy Emotions|Sadness": -0.9805308286957324,
    "Longing & Lust|Infatuation": -1.6358114046082173,
    "Negative Low-Energy Emotions|Bitterness": -1.831962204586046
  }
}