{
  "key": [
    "stance-detection-part-9",
    "emonet-m1",
    "flux_prompt_9-image_244.png"
  ],
  "value": {
    "Positive Low-Energy Emotions|Affection": 1.6344419839884063,
    "Positive High-Energy Emotions|Interest": 1.6053020199521995,
    "Positive Low-Energy Emotions|Pride": 1.5196144086796612,
    "Cognitive States and Processes|Concentration": 1.4758460795295325,
    "Positive Low-Energy Emotions|Contentment": 1.1414798306772014,
    "Longing & Lust|Sexual Lust": 1.1393599124291005,
    "Extra Dimensions|Valence": 1.0269685829605826,
    "Positive Low-Energy Emotions|Contemplation": 1.0148993953721317,
    "Longing & Lust|Longing": 0.8922998080432634,
    "Positive High-Energy Emotions|Hope/Enthusiasm/Optimism": 0.8788256391050505,
    "Extra Dimensions|Dominance": 0.8210846626680794,
    "Positive High-Energy Emotions|Pleasure/Ecstasy": 0.6459215122480891,
    "Negative High-Energy Emotions|Anger": 0.6431278368055602,
    "Longing & Lust|Infatuation": 0.409365585722002,
    "Physical and Exhaustive States|Fatigue/Exhaustion": 0.19061364553486693,
    "Negative High-Energy Emotions|Impatience and Irritability": 0.128717424771015,
    "Positive Low-Energy Emotions|Relief": 0.00244611460074182,
    "Negative Low-Energy Emotions|Jealousy & Envy": 0.0,
    "Negative Low-Energy Emotions|Emotional Numbness": -0.005786408844229873,
    "Physical and Exhaustive States|Intoxication/Altered States of Consciousness": -0.008975118473718019,
    "Physical and Exhaustive States|Sourness": -0.014062261945762477,
    "Positive High-Energy Emotions|Awe": -0.014155245021040187,
    "Physical and Exhaustive States|Pain": -0.020670116004905786,
    "Positive High-Energy Emotions|Astonishment/Surprise": -0.0323686634801028,
    "Negative High-Energy Emotions|Disgust": -0.038352960850292946,
    "Positive High-Energy Emotions|Triumph": -0.06611545954834357,
    "Extra Dimensions|Arousal": -0.1108480777059282,
    "Negative Low-Energy Emotions|Embarrassment": -0.11775220399756571,
    "Positive High-Energy Emotions|Teasing": -0.12323280301750143,
    "Negative High-Energy Emotions|Fear": -0.13712736746917167,
    "Positive High-Energy Emotions|Elation": -0.15317291597865035,
    "Cognitive States and Processes|Confusion": -0.17613116730918815,
    "Extra Dimensions|Emotional Vulnerability": -0.1818828274915507,
    "Negative Low-Energy Emotions|Helplessness": -0.1944561482854051,
    "Negative Low-Energy Emotions|Contempt": -0.369194353828309,
    "Negative Low-Energy Emotions|Sadness": -0.4428481305874765,
    "Positive Low-Energy Emotions|Thankfulness/Gratitude": -0.47464723604767084,
    "Positive High-Energy Emotions|Amusement": -0.5141683372740562,
    "Negative High-Energy Emotions|Distress": -0.5272634312742468,
    "Negative High-Energy Emotions|Malevolence/Malice": -0.5330728653190664,
    "Negative Low-Energy Emotions|Doubt": -0.5590526150537811,
    "Negative Low-Energy Emotions|Shame": -0.6563885436191192,
    "Negative Low-Energy Emotions|Disappointment": -0.73963793411155,
    "Negative Low-Energy Emotions|Bitterness": -1.8303487170965245
  }
}