{
  "key": [
    "stance-detection-part-2",
    "emonet-m1",
    "mj_data_280_U3.png"
  ],
  "value": {
    "Negative High-Energy Emotions|Anger": 2.3530475278913756,
    "Physical and Exhaustive States|Pain": 2.341155941949298,
    "Cognitive States and Processes|Concentration": 2.2039809500587073,
    "Negative High-Energy Emotions|Distress": 1.84025029984777,
    "Positive Low-Energy Emotions|Contemplation": 1.4284657463090213,
    "Physical and Exhaustive States|Fatigue/Exhaustion": 1.2471596183589635,
    "Extra Dimensions|Dominance": 0.9745035612505379,
    "Negative Low-Energy Emotions|Sadness": 0.8275200282298147,
    "Positive High-Energy Emotions|Hope/Enthusiasm/Optimism": 0.7509643777372527,
    "Negative Low-Energy Emotions|Helplessness": 0.6882381855063276,
    "Negative High-Energy Emotions|Impatience and Irritability": 0.6549310707060736,
    "Negative Low-Energy Emotions|Contempt": 0.49377675085318284,
    "Negative High-Energy Emotions|Fear": 0.3013805247222384,
    "Positive High-Energy Emotions|Interest": 0.18815748298015356,
    "Negative High-Energy Emotions|Disgust": 0.14235424051136325,
    "Positive Low-Energy Emotions|Pride": 0.12473459071701476,
    "Negative Low-Energy Emotions|Emotional Numbness": 0.0032366614911583103,
    "Positive Low-Energy Emotions|Relief": 0.0014408524642824695,
    "Negative Low-Energy Emotions|Jealousy & Envy": 0.0,
    "Positive High-Energy Emotions|Awe": -0.0013537915498564104,
    "Physical and Exhaustive States|Sourness": -0.012108466393508753,
    "Physical and Exhaustive States|Intoxication/Altered States of Consciousness": -0.01576663561219916,
    "Positive Low-Energy Emotions|Affection": -0.03961263866174014,
    "Negative Low-Energy Emotions|Bitterness": -0.04109824081070923,
    "Positive High-Energy Emotions|Pleasure/Ecstasy": -0.05585866253574567,
    "Positive High-Energy Emotions|Astonishment/Surprise": -0.058093119194328566,
    "Positive High-Energy Emotions|Triumph": -0.07605465793054238,
    "Positive High-Energy Emotions|Teasing": -0.11904916045129736,
    "Negative Low-Energy Emotions|Embarrassment": -0.11961167892475268,
    "Positive High-Energy Emotions|Elation": -0.1531739974788091,
    "Cognitive States and Processes|Confusion": -0.1830590077208512,
    "Extra Dimensions|Arousal": -0.22945202248437058,
    "Positive Low-Energy Emotions|Contentment": -0.4795911503484944,
    "Positive Low-Energy Emotions|Thankfulness/Gratitude": -0.4809325309380746,
    "Positive High-Energy Emotions|Amusement": -0.5262992124144847,
    "Negative High-Energy Emotions|Malevolence/Malice": -0.5266444894788793,
    "Negative Low-Energy Emotions|Shame": -0.6598205064221254,
    "Longing & Lust|Sexual Lust": -0.66052428766703,
    "Longing & Lust|Longing": -0.6856968631565352,
    "Extra Dimensions|Emotional Vulnerability": -0.7208219458768657,
    "Negative Low-Energy Emotions|Disappointment": -0.7331786625762726,
    "Negative Low-Energy Emotions|Doubt": -0.9101685719562851,
    "Extra Dimensions|Valence": -1.001388982442402,
    "Longing & Lust|Infatuation": -1.6329677266106282
  }
}