{
  "key": [
    "stance-detection-part-4",
    "emonet-m1",
    "mj_data_41_U1.png"
  ],
  "value": {
    "Negative Low-Energy Emotions|Embarrassment": 3.6021311783228382,
    "Cognitive States and Processes|Confusion": 3.13774291346798,
    "Negative High-Energy Emotions|Distress": 2.456893490231681,
    "Negative Low-Energy Emotions|Disappointment": 1.9477587412367319,
    "Negative Low-Energy Emotions|Sadness": 1.771182910081011,
    "Negative High-Energy Emotions|Impatience and Irritability": 1.6689604543654364,
    "Negative Low-Energy Emotions|Doubt": 1.5283988429235138,
    "Physical and Exhaustive States|Fatigue/Exhaustion": 1.406045931797379,
    "Negative Low-Energy Emotions|Contempt": 1.3357191207910795,
    "Negative Low-Energy Emotions|Bitterness": 0.8806346617161462,
    "Extra Dimensions|Emotional Vulnerability": 0.6440286944200704,
    "Negative High-Energy Emotions|Anger": 0.6229664465009948,
    "Negative High-Energy Emotions|Disgust": 0.6027583087429459,
    "Negative Low-Energy Emotions|Helplessness": 0.6017538724951582,
    "Positive Low-Energy Emotions|Contemplation": 0.5559746250169071,
    "Cognitive States and Processes|Concentration": 0.4687335764777747,
    "Negative High-Energy Emotions|Fear": 0.3051252461348971,
    "Positive High-Energy Emotions|Interest": 0.2666093548521018,
    "Positive High-Energy Emotions|Astonishment/Surprise": 0.08793306000012181,
    "Negative Low-Energy Emotions|Emotional Numbness": 0.059031138953926865,
    "Physical and Exhaustive States|Intoxication/Altered States of Consciousness": 0.002855680807879119,
    "Negative Low-Energy Emotions|Jealousy & Envy": 0.0,
    "Physical and Exhaustive States|Sourness": -0.0023570123978041025,
    "Positive Low-Energy Emotions|Relief": -0.009347185908711,
    "Positive High-Energy Emotions|Awe": -0.011865636900121913,
    "Physical and Exhaustive States|Pain": -0.020670116004905786,
    "Positive High-Energy Emotions|Pleasure/Ecstasy": -0.055859311611646256,
    "Positive High-Energy Emotions|Triumph": -0.07402076118629113,
    "Positive High-Energy Emotions|Teasing": -0.1280718955105587,
    "Extra Dimensions|Arousal": -0.15303052323205124,
    "Positive High-Energy Emotions|Elation": -0.15317486443644368,
    "Negative High-Energy Emotions|Malevolence/Malice": -0.44715072841625725,
    "Positive Low-Energy Emotions|Thankfulness/Gratitude": -0.48164783510415315,
    "Positive High-Energy Emotions|Amusement": -0.5274776819233711,
    "Extra Dimensions|Dominance": -0.5373591935712394,
    "Negative Low-Energy Emotions|Shame": -0.5429315465300313,
    "Longing & Lust|Sexual Lust": -0.6730413524768292,
    "Longing & Lust|Longing": -0.8828509976684829,
    "Positive Low-Energy Emotions|Affection": -1.0520467561577538,
    "Positive Low-Energy Emotions|Pride": -1.1172490092437892,
    "Positive High-Energy Emotions|Hope/Enthusiasm/Optimism": -1.2862028733728241,
    "Extra Dimensions|Valence": -1.3457759772811166,
    "Longing & Lust|Infatuation": -1.6445849326476727,
    "Positive Low-Energy Emotions|Contentment": -1.657203261320899
  }
}