{
  "key": [
    "stance-detection-part-10",
    "emonet-m1",
    "flux_prompt_10-image_288.png"
  ],
  "value": {
    "Cognitive States and Processes|Concentration": 2.4990134512794104,
    "Positive High-Energy Emotions|Pleasure/Ecstasy": 2.439640565516522,
    "Positive High-Energy Emotions|Awe": 2.3050631372183017,
    "Positive High-Energy Emotions|Hope/Enthusiasm/Optimism": 1.8510921939375091,
    "Positive Low-Energy Emotions|Contemplation": 1.7423857673661503,
    "Positive Low-Energy Emotions|Contentment": 1.254593710834672,
    "Positive High-Energy Emotions|Interest": 1.1858796318754172,
    "Positive Low-Energy Emotions|Affection": 0.9183479669595978,
    "Physical and Exhaustive States|Fatigue/Exhaustion": 0.7953062238506018,
    "Extra Dimensions|Valence": 0.7916698301758536,
    "Longing & Lust|Longing": 0.6009191641986589,
    "Positive High-Energy Emotions|Astonishment/Surprise": 0.45425983912724277,
    "Negative High-Energy Emotions|Impatience and Irritability": 0.3917893194167059,
    "Negative High-Energy Emotions|Anger": 0.3267507930815002,
    "Positive High-Energy Emotions|Triumph": 0.027195867961238476,
    "Positive Low-Energy Emotions|Relief": 0.003941222609126525,
    "Negative Low-Energy Emotions|Jealousy & Envy": 0.0,
    "Positive High-Energy Emotions|Amusement": -0.0019559416060264123,
    "Physical and Exhaustive States|Sourness": -0.0153347391553305,
    "Physical and Exhaustive States|Pain": -0.020670116004905786,
    "Physical and Exhaustive States|Intoxication/Altered States of Consciousness": -0.028562918380448672,
    "Negative High-Energy Emotions|Disgust": -0.04062696745544126,
    "Negative Low-Energy Emotions|Emotional Numbness": -0.04744343942665785,
    "Extra Dimensions|Dominance": -0.04825605512443151,
    "Negative Low-Energy Emotions|Embarrassment": -0.11717754444141527,
    "Positive High-Energy Emotions|Teasing": -0.1202106612628742,
    "Negative High-Energy Emotions|Fear": -0.123891142817835,
    "Positive High-Energy Emotions|Elation": -0.14951700165409632,
    "Cognitive States and Processes|Confusion": -0.1757389314936631,
    "Negative Low-Energy Emotions|Helplessness": -0.19052836610748,
    "Negative Low-Energy Emotions|Contempt": -0.3759556812142114,
    "Positive Low-Energy Emotions|Thankfulness/Gratitude": -0.48085222858040094,
    "Extra Dimensions|Arousal": -0.5189749087606157,
    "Negative High-Energy Emotions|Malevolence/Malice": -0.5282054457185796,
    "Extra Dimensions|Emotional Vulnerability": -0.5388055731962016,
    "Negative Low-Energy Emotions|Sadness": -0.6056377137936533,
    "Negative Low-Energy Emotions|Shame": -0.6563087097167006,
    "Negative High-Energy Emotions|Distress": -0.661495706462216,
    "Longing & Lust|Infatuation": -0.6622888532504712,
    "Longing & Lust|Sexual Lust": -0.6657415567300259,
    "Positive Low-Energy Emotions|Pride": -0.7380908625643878,
    "Negative Low-Energy Emotions|Disappointment": -0.7397067290474917,
    "Negative Low-Energy Emotions|Doubt": -0.9399351315571152,
    "Negative Low-Energy Emotions|Bitterness": -1.8305725222931077
  }
}